{
  "os":  "Linux-5.14.0-284.11.1.el9_2_cifs.x86_64-x86_64-with-glibc2.34",
  "python":  "CPython 3.10.19",
  "startedAt":  "2025-12-11T02:28:36.152234Z",
  "args":  [
    "--data_path",
    "preprocessing/data/final_train_data.txt",
    "--vocab_path",
    "preprocessing/data/vocab.json",
    "--output_dir",
    "output",
    "--d_model",
    "32",
    "--num_layers",
    "1",
    "--num_heads",
    "2",
    "--ff_dim",
    "32",
    "--dropout_rate",
    "0.1",
    "--deep_rec_cycles",
    "1",
    "--num_l_steps",
    "2",
    "--deep_sup_steps",
    "2",
    "--act_loss_weight",
    "0.1",
    "--epochs",
    "30",
    "--batch_size",
    "8",
    "--learning_rate",
    "1e-4",
    "--max_seq_length",
    "128"
  ],
  "program":  "/oscar/home/bpeckham/TinyAI/train.py",
  "codePath":  "train.py",
  "codePathLocal":  "train.py",
  "git":  {
    "remote":  "git@github.com:rajveer-sodhi/TinyAI.git",
    "commit":  "4a0c013f30b9f729f94548c5c934d70e8720aba5"
  },
  "email":  "benjamin_peckham@brown.edu",
  "root":  "/oscar/home/bpeckham/TinyAI",
  "host":  "gpu2006.oscar.ccv.brown.edu",
  "executable":  "/users/bpeckham/.conda/envs/tinyai/bin/python",
  "cpu_count":  32,
  "cpu_count_logical":  32,
  "gpu":  "Quadro RTX 6000",
  "gpu_count":  1,
  "disk":  {
    "/":  {
      "total":  "201618690048",
      "used":  "9132994560"
    }
  },
  "memory":  {
    "total":  "403237384192"
  },
  "gpu_nvidia":  [
    {
      "name":  "Quadro RTX 6000",
      "memoryTotal":  "25769803776",
      "cudaCores":  4608,
      "architecture":  "Turing",
      "uuid":  "GPU-0d346854-ed70-597e-08e9-a91a57229869"
    }
  ],
  "cudaVersion":  "12.2",
  "slurm":  {
    "cluster_name":  "(null)",
    "conf":  "/var/spool/slurmd/conf-cache/slurm.conf",
    "cpus_on_node":  "4",
    "cpus_per_task":  "4",
    "gpus_on_node":  "1",
    "gtids":  "0",
    "job_account":  "default",
    "job_cpus_per_node":  "4",
    "job_end_time":  "1765432755",
    "job_gid":  "20055",
    "job_gpus":  "1",
    "job_id":  "14792241",
    "job_name":  "TinyAI",
    "job_nodelist":  "gpu2006",
    "job_num_nodes":  "1",
    "job_partition":  "gpu",
    "job_qos":  "norm-gpu",
    "job_start_time":  "1765418355",
    "job_uid":  "140630026",
    "job_user":  "bpeckham",
    "jobid":  "14792241",
    "localid":  "0",
    "mem_per_node":  "64000",
    "nnodes":  "1",
    "nodeid":  "0",
    "nodelist":  "gpu2006",
    "nprocs":  "1",
    "ntasks":  "1",
    "ntasks_per_node":  "1",
    "prio_process":  "0",
    "procid":  "0",
    "script_context":  "prolog_task",
    "submit_dir":  "/oscar/home/bpeckham/TinyAI",
    "submit_host":  "login009",
    "task_pid":  "3937408",
    "tasks_per_node":  "1",
    "topology_addr":  "gpu5.gpu2006",
    "topology_addr_pattern":  "switch.node",
    "tres_per_task":  "cpu:4"
  },
  "writerId":  "7z875ss2lx37a0z6narhinulybty2gca"
}